{
  "geoserver": "minplanifica",
  "fuente": "Geoserver del Ministerio de Planificación del Desarollo",
  "ows": "https://geoserver.planificacion.gob.bo/geoserver/ows",
  "nombre": "infocapa:layer_ecorregiones_1_xawjk",
  "titulo": "layer_ecorregiones_1_xawjk",
  "descripcion": "",
  "fecha_archivado": "2026-04-15",
  "archive_item": "geodatosbolivia_minplanifica_infocapa_layer_ecorregiones_1_xawjk",
  "epsg": 4326,
  "bbox": {
    "min_x": -69.712532,
    "max_x": -57.393215,
    "min_y": -22.972027,
    "max_y": -9.590257
  },
  "n_features": 676
}