{
  "geoserver": "lapaz.sit",
  "fuente": "Sistema de Información Territorial del Gobierno Autónomo Municipal de La Paz",
  "ows": "http://sitservicios.lapaz.bo/geoserver/ows",
  "nombre": "patrimonio:tramosPatrimoniales",
  "titulo": "Tramos Patrimoniales",
  "descripcion": "Tramos Patrimoniales, LM 17/2025.",
  "fecha_archivado": "2026-05-30",
  "archive_item": "geodatosbolivia_lapaz_sit_patrimonio_tramospatrimoniales",
  "epsg": 32719,
  "bbox": {
    "min_x": -68.142697,
    "max_x": -68.107022,
    "min_y": -16.529358,
    "max_y": -16.490402
  },
  "n_features": 42
}