{
  "geoserver": "lapaz.sit",
  "fuente": "Sistema de Información Territorial del Gobierno Autónomo Municipal de La Paz",
  "ows": "http://sitservicios.lapaz.bo/geoserver/ows",
  "nombre": "lapaz:cuencahidrografica",
  "titulo": "Cuenca Hidrografica",
  "descripcion": "Cuencas hidrográficas Municipio de La Paz, SMGVA",
  "fecha_archivado": "2026-05-30",
  "archive_item": "geodatosbolivia_lapaz_sit_lapaz_cuencahidrografica",
  "epsg": 32719,
  "bbox": {
    "min_x": -68.186462,
    "max_x": -67.934324,
    "min_y": -16.621783,
    "max_y": -16.30055
  },
  "n_features": 10
}