{
  "id": "festividades2.1",
  "IdFestividad": 1,
  "Lugar": "Municipio de La Paz (Todas las Iglesias y Parroquias de La Paz)",
  "Macrodistrito": "Siete macrodistritos urbanos (Cotahuma, Max Paredes, Periférica, Centro, San Antonio, Sur, Mallasa)",
  "IdMacrodistrito": 0.0,
  "Distrito": 0.0,
  "DistritoMcpal": "Todos los distritos urbanos y dos distritos rurales (Zongo 23,Hampaturi 22)",
  "NoUbicable": 1.0,
  "NroFraternidades": "Iglesia Católica",
  "Responsables": "Arzobispado",
  "owner": null,
  "usuario": "clara.revollo",
  "fechaActual": null,
  "observaciones": "",
  "TipoCalendario": "CALENDARIO CATÓLICO",
  "Festividad": "Celebración del Año Nuevo Católico",
  "Mes": 1,
  "Fecha": "01 DE ENERO",
  "Descripcion": "Antiguamente el calendario romano comenzaba el primer día del mes de Marzo. Sin embargo, era en el mes de Enero  cuando los cónsules de la Antigua Roma asumían el gobierno y  por eso Julio César, en el año 47 a. C., modificó el sistema y creó el calendario juliano que, con algunas modificaciones realizadas en tiempos del cónsul Marco Antonio en 44 a. C., el emperador Augusto César en 8 a. C. y finalmente por el papa Gregorio XIII en 1582, se utiliza hasta hoy. En éste el año comienza el día 1 de Enero. En Bolivia se declara feriado nacional con suspensión de actividades  mediante el Decreto supremo N° 26597. En la ciudad de La Paz se realizan diferentes actividades y prácticas muchas de las cuales provienen del mundo occidental. Generalmente la fiesta comienza la noche del 31 de Diciembre con música y comida, que por lo general es preparada con carne de cerdo, porque esta asociado con la abundancia y la prosperidad, la cual se comparte mientras se espera la media noche para “recibir” un nuevo año y el paso de un ciclo a otro.   "
}