{
  "geoserver": "mhe.geoportal",
  "fuente": "Geoportal del Viceministerio de Electricidad y Energías Renovables",
  "ows": "https://geoportal.mhe.gob.bo/geoserver/ows",
  "nombre": "geonode:Media_Ten_20220",
  "titulo": "Media_Ten_20220",
  "descripcion": "",
  "fecha_archivado": "2026-04-12",
  "archive_item": "geodatosbolivia_mhe_geoportal_geonode_media_ten_20220",
  "epsg": 4326,
  "bbox": {
    "min_x": -69.606243,
    "max_x": -57.700456,
    "min_y": -22.865041,
    "max_y": -10.522061
  },
  "n_features": 242
}