{
  "id": "layer_vegetacion_del_municpio_de_montero__ptdi_e6xyn.1",
  "cod_vegeta": "ba",
  "tipo_veget": "Áreas antrópicas",
  "codigo_": "CES406.Beni",
  "sistema_de": "5. Llanos del Sara",
  "conservaci": "A0",
  "descrip_co": "Transformado",
  "proteccion": "EX",
  "descrip_pr": "Extinto",
  "potencial": "0",
  "descrip_po": "Áreas antrópicas",
  "cod_veg_si": "80",
  "nomb_veg_s": "Áreas antrópicas",
  "sup_ha": 34.588,
  "dep": "Santa Cruz",
  "prov": "Obispo Santisteban",
  "mun": "Montero"
}