{
  "id": "layer_crecimiento_de_la_mancha_urba__ptdi_wlipfj.478",
  "descripcio": "Mancha Urbana del año 2021",
  "total_viv": 0,
  "radio": 0,
  "tv": 0,
  "compu": 0,
  "internet": 0,
  "telefono": 0,
  "vehiculo": 0,
  "bicicleta": 0,
  "moto": 0,
  "carreta": 0,
  "bote": 0,
  "pared_ladr": 0,
  "adobe_con": 0,
  "adobe_sin": 0,
  "tabique": 0,
  "piedra": 0,
  "madera": 0,
  "canha": 0,
  "pared_otro": 0,
  "techo_cala": 0,
  "teja": 0,
  "hormigon": 0,
  "paja": 0,
  "techo_otro": 0,
  "piso_tierr": 0,
  "tablon": 0,
  "machimbre": 0,
  "parquet": 0,
  "ceramica": 0,
  "cemento": 0,
  "mosaico": 0,
  "ladrillo": 0,
  "piso_otro": 0,
  "sup_ha": 0.71,
  "dep": "Santa Cruz",
  "prov": "Obispo Santisteban",
  "mun": "Montero"
}