{
  "geoserver": "planificacion.geoinfo",
  "fuente": "Sistema GeoInfo del Ministerio de Planificación",
  "ows": "https://geoinfo.planificacion.gob.bo/geoserver/ows",
  "nombre": "infospie:layer_corredor_fluvial_pnot_lbklzg",
  "titulo": "layer_corredor_fluvial_pnot_lbklzg",
  "descripcion": "",
  "fecha_archivado": "2026-04-14",
  "archive_item": "geodatosbolivia_planificacion_geoinfo_infospie_layer_corredor_fluvial_pnot_lbklzg",
  "epsg": 4326,
  "bbox": {
    "min_x": -60.772224,
    "max_x": -57.150859,
    "min_y": -33.951998,
    "max_y": -18.952459
  },
  "n_features": 6
}