{
  "fid": 1,
  "gml_id": "Limites_municipales.6",
  "ID": 224,
  "CODSECCION": "080202",
  "CODIGO": "080202",
  "COD_DEP": "8",
  "NOM_DEP": "Beni",
  "COD_PROV": "2",
  "NOM_PROV": "Vaca Diez",
  "COD_MUN": "2",
  "CAT_SEC": "SEGUNDA",
  "NOM_MUN": "Guayaramerín",
  "CANTONES": "4",
  "POBLACION": "32273",
  "MUNIDE": 293,
  "Shape_Leng": 6.06132067,
  "created_us": "",
  "created_da": null,
  "last_edite": "",
  "last_edi_1": null,
  "Shape_STAr": 6502158727.78,
  "Shape_STLe": 666598.878873
}