{
  "geoserver": "mmaya.oieau",
  "fuente": "Sistema para la Gestión Integral de Recursos Hídricos desarrollado por la Oficina Internacional del Agua (OiEau)",
  "ows": "https://www.oieau-wiss.org/geoserver/ows",
  "nombre": "c_cv:freguesia_polygon",
  "titulo": "CV_AD_freguesia_polygon",
  "descripcion": "",
  "fecha_archivado": "2026-04-15",
  "archive_item": "geodatosbolivia_mmaya_oieau_c_cv_freguesia_polygon",
  "epsg": 4326,
  "bbox": {
    "min_x": -25.361188,
    "max_x": -22.657562,
    "min_y": 14.802617,
    "max_y": 17.205161
  },
  "n_features": 32
}