{
  "geoserver": "minplanifica",
  "fuente": "Geoserver del Ministerio de Planificación del Desarollo",
  "ows": "https://geoserver.planificacion.gob.bo/geoserver/ows",
  "nombre": "infocapa:layer_centrales_generadoras_sin_2022_xn20f",
  "titulo": "layer_centrales_generadoras_sin_2022_xn20f",
  "descripcion": "",
  "fecha_archivado": "2026-04-14",
  "archive_item": "geodatosbolivia_minplanifica_infocapa_layer_centrales_generadoras_sin_2022_xn20f",
  "epsg": 4326,
  "bbox": {
    "min_x": -68.181144,
    "max_x": -62.838045,
    "min_y": -21.835192,
    "max_y": -13.747522
  },
  "n_features": 55
}