{
  "FID_cuenca": 0,
  "NIVEL_UH": "Multinivel",
  "NOMBRE": "Cuenca Rio Katari - Lago Menor",
  "COD_PFAF": "0153 - 0157 - 0158 - 01592 - 01593 - 01594 - 01596",
  "NIVEL": "Multinivel (Nivel 4 y 5)",
  "SUP_KM2": 6352.16,
  "CLASIFIC": "Subcuenca",
  "FID_Munici": 111,
  "OBJECTID": 112,
  "DEPARTAMEN": "La Paz",
  "PROVINCIA": "Aroma",
  "MUNICIPIO": "Collana",
  "CAPITAL": "Collana",
  "F_LEY_PROV": "1945-11-23T04:00:00Z",
  "LEY_MUN": "823",
  "F_LEY_MUN": "1986-04-03T04:00:00Z",
  "TIOC": "",
  "X": -68.3011802329,
  "Y": -16.903720427,
  "MUN_ALTERN": "Collana",
  "Observ": "",
  "Mun_Selecc": "",
  "HELVETAS": "",
  "CICan": "",
  "SSalesiana": "",
  "ICCO": "",
  "CRECER": "",
  "ONU_Mujer": "",
  "HI": "",
  "Emp_Suiza": ""
}